<DOMSymbolItem xmlns="http://ns.adobe.com/xfl/2008/" xmlns:xsi="http://www.w3.org/2001/XMLSchema-instance" name="Symbol 366" itemID="689b8880-000000e0" lastModified="1703808239" symbolType="graphic">
     <timeline>
          <DOMTimeline name="Symbol 366" currentFrame="0">
               <layers>
                    <DOMLayer name="Layer 1">
                         <frames>
                              <DOMFrame index="0" motionTweenScale="false" keyMode="8192">
                                   <elements>
                                        <DOMShape isFloating="true">
                                             <fills>
                                                  <FillStyle index="1">
                                                       <SolidColor color="#425c80"/>
                                                  </FillStyle>
                                             </fills>
                                             <strokes/>
                                             <edges>
                                                  <Edge fillStyle0="0" fillStyle1="1" strokeStyle="0" edges="! 4975 3114[ 4996 3094 4996 3065| 4996 3064[ 4996 3035 4975 3014[ 4956 2995 4928 2994| 5000 2994| 5000 3139| 393 3139| 393 3067[ 394 3095 413 3114[ 434 3135 463 3135| 4926 3135[ 4955 3135 4975 3114"/>
                                                  <Edge fillStyle0="0" fillStyle1="1" strokeStyle="0" edges="! 393 3062| 393 2994| 461 2994[ 433 2995 413 3014[ 394 3034 393 3062"/>
                                             </edges>
                                        </DOMShape>
                                   </elements>
                              </DOMFrame>
                         </frames>
                    </DOMLayer>
                    <DOMLayer name="Layer 2">
                         <frames>
                              <DOMFrame index="0" motionTweenScale="false" keyMode="8192">
                                   <elements>
                                        <DOMShape isFloating="true">
                                             <fills>
                                                  <FillStyle index="1">
                                                       <SolidColor color="#365080"/>
                                                  </FillStyle>
                                             </fills>
                                             <strokes/>
                                             <edges>
                                                  <Edge fillStyle0="0" fillStyle1="1" strokeStyle="0" edges="! 4976 1839[ 4954 1817 4921 1816| 5000 1816| 5000 1895[ 4999 1862 4976 1839"/>
                                                  <Edge fillStyle0="0" fillStyle1="1" strokeStyle="0" edges="! 5000 1900| 5000 1979| 4921 1979[ 4954 1978 4976 1955[ 4999 1933 5000 1900"/>
                                                  <Edge fillStyle0="0" fillStyle1="1" strokeStyle="0" edges="! 2996 1816| 3075 1816[ 3042 1817 3019 1839[ 2997 1862 2996 1895| 2996 1816"/>
                                                  <Edge fillStyle0="0" fillStyle1="1" strokeStyle="0" edges="! 2996 1900[ 2997 1933 3019 1955[ 3042 1978 3075 1979| 2996 1979| 2996 1900"/>
                                             </edges>
                                        </DOMShape>
                                   </elements>
                              </DOMFrame>
                         </frames>
                    </DOMLayer>
                    <DOMLayer name="Layer 3">
                         <frames>
                              <DOMFrame index="0" motionTweenScale="false" keyMode="8192">
                                   <elements>
                                        <DOMShape isFloating="true">
                                             <fills>
                                                  <FillStyle index="1">
                                                       <SolidColor color="#365080"/>
                                                  </FillStyle>
                                             </fills>
                                             <strokes/>
                                             <edges>
                                                  <Edge fillStyle0="0" fillStyle1="1" strokeStyle="0" edges="! 5000 695[ 4999 662 4976 639[ 4954 617 4921 616| 5000 616| 5000 695"/>
                                                  <Edge fillStyle0="0" fillStyle1="1" strokeStyle="0" edges="! 4976 755[ 4999 733 5000 700| 5000 779| 4921 779[ 4954 778 4976 755"/>
                                                  <Edge fillStyle0="0" fillStyle1="1" strokeStyle="0" edges="! 2996 695| 2996 616| 3075 616[ 3042 617 3019 639[ 2997 662 2996 695"/>
                                                  <Edge fillStyle0="0" fillStyle1="1" strokeStyle="0" edges="! 2996 779| 2996 700[ 2997 733 3019 755[ 3042 778 3075 779| 2996 779"/>
                                             </edges>
                                        </DOMShape>
                                   </elements>
                              </DOMFrame>
                         </frames>
                    </DOMLayer>
                    <DOMLayer name="Layer 4">
                         <frames>
                              <DOMFrame index="0" motionTweenScale="false" keyMode="8192">
                                   <elements>
                                        <DOMShape isFloating="true">
                                             <fills>
                                                  <FillStyle index="1">
                                                       <SolidColor color="#365080"/>
                                                  </FillStyle>
                                             </fills>
                                             <strokes/>
                                             <edges>
                                                  <Edge fillStyle0="0" fillStyle1="1" strokeStyle="0" edges="! 2400 1796| 2400 1875[ 2399 1842 2376 1819[ 2354 1797 2321 1796| 2400 1796"/>
                                                  <Edge fillStyle0="0" fillStyle1="1" strokeStyle="0" edges="! 2321 1959[ 2354 1958 2376 1935[ 2399 1913 2400 1880| 2400 1959| 2321 1959"/>
                                                  <Edge fillStyle0="0" fillStyle1="1" strokeStyle="0" edges="! 419 1819[ 397 1842 396 1875| 396 1796| 475 1796[ 442 1797 419 1819"/>
                                                  <Edge fillStyle0="0" fillStyle1="1" strokeStyle="0" edges="! 475 1959| 396 1959| 396 1880[ 397 1913 419 1935[ 442 1958 475 1959"/>
                                             </edges>
                                        </DOMShape>
                                   </elements>
                              </DOMFrame>
                         </frames>
                    </DOMLayer>
                    <DOMLayer name="Layer 5">
                         <frames>
                              <DOMFrame index="0" motionTweenScale="false" keyMode="8192">
                                   <elements>
                                        <DOMShape isFloating="true">
                                             <fills>
                                                  <FillStyle index="1">
                                                       <SolidColor color="#365080"/>
                                                  </FillStyle>
                                             </fills>
                                             <strokes/>
                                             <edges>
                                                  <Edge fillStyle0="0" fillStyle1="1" strokeStyle="0" edges="! 2321 596| 2400 596| 2400 675[ 2399 642 2376 619[ 2354 597 2321 596"/>
                                                  <Edge fillStyle0="0" fillStyle1="1" strokeStyle="0" edges="! 2400 759| 2321 759[ 2354 758 2376 735[ 2399 713 2400 680| 2400 759"/>
                                                  <Edge fillStyle0="0" fillStyle1="1" strokeStyle="0" edges="! 475 596[ 442 597 419 619[ 397 642 396 675| 396 596| 475 596"/>
                                                  <Edge fillStyle0="0" fillStyle1="1" strokeStyle="0" edges="! 419 735[ 442 758 475 759| 396 759| 396 680[ 397 713 419 735"/>
                                             </edges>
                                        </DOMShape>
                                   </elements>
                              </DOMFrame>
                         </frames>
                    </DOMLayer>
               </layers>
          </DOMTimeline>
     </timeline>
</DOMSymbolItem>
